devduck/__init__.py
devduck/__main__.py
devduck/_version.py
devduck/agentcore_handler.py
devduck/test_redduck.py
devduck/tools/__init__.py
devduck/tools/_ambient_input.py
devduck/tools/_tray_app.py
devduck/tools/agentcore_agents.py
devduck/tools/agentcore_config.py
devduck/tools/agentcore_invoke.py
devduck/tools/agentcore_logs.py
devduck/tools/ambient.py
devduck/tools/create_subagent.py
devduck/tools/fetch_github_tool.py
devduck/tools/install_tools.py
devduck/tools/ipc.py
devduck/tools/mcp_server.py
devduck/tools/scraper.py
devduck/tools/speech_to_speech.py
devduck/tools/state_manager.py
devduck/tools/store_in_kb.py
devduck/tools/system_prompt.py
devduck/tools/tcp.py
devduck/tools/tray.py
devduck/tools/use_github.py
devduck/tools/websocket.py
devduck-1.2.0.dist-info/licenses/LICENSE
devduck-1.2.0.dist-info/METADATA
devduck-1.2.0.dist-info/WHEEL
devduck-1.2.0.dist-info/entry_points.txt
devduck-1.2.0.dist-info/top_level.txt
devduck-1.2.0.dist-info/RECORD
