Metadata-Version: 2.4
Name: devduck
Version: 1.2.0
Summary: 🦆 Self-adapting agent - one file.
Author-email: Cagatay Cali <cagataycali@icloud.com>
License: Apache-2.0
Project-URL: Homepage, https://github.com/cagataycali/devduck
Project-URL: Repository, https://github.com/cagataycali/devduck.git
Project-URL: Documentation, https://github.com/cagataycali/devduck#readme
Project-URL: Bug Tracker, https://github.com/cagataycali/devduck/issues
Keywords: ai,agent,minimalist,self-healing,ollama,strands-agents
Classifier: Development Status :: 4 - Beta
Classifier: Environment :: Console
Classifier: Intended Audience :: Developers
Classifier: Intended Audience :: System Administrators
Classifier: Operating System :: OS Independent
Classifier: Programming Language :: Python :: 3
Classifier: Programming Language :: Python :: 3.10
Classifier: Programming Language :: Python :: 3.11
Classifier: Programming Language :: Python :: 3.12
Classifier: Programming Language :: Python :: 3.13
Classifier: Topic :: Scientific/Engineering :: Artificial Intelligence
Classifier: Topic :: Software Development :: Libraries :: Python Modules
Classifier: Topic :: System :: Systems Administration
Classifier: Topic :: Utilities
Requires-Python: <3.14,>=3.10
License-File: LICENSE
Requires-Dist: strands-agents
Requires-Dist: prompt_toolkit
Requires-Dist: strands-agents[ollama]
Requires-Dist: strands-agents[anthropic]
Requires-Dist: strands-agents[openai]
Requires-Dist: strands-agents[otel]
Requires-Dist: strands-agents-tools
Requires-Dist: beautifulsoup4
Requires-Dist: colorama
Requires-Dist: websockets
Requires-Dist: strands-mcp-server
Requires-Dist: strands-google
Requires-Dist: bedrock-agentcore-starter-toolkit
Requires-Dist: bedrock-agentcore
Requires-Dist: rumps; sys_platform == "darwin"
Requires-Dist: strands-mlx; sys_platform == "darwin"
Provides-Extra: speech
Requires-Dist: strands-agents[bidi-all]; extra == "speech"
Dynamic: license-file
